{"cameraMode":{"drawMode":0,"name":"Shaded","section":"Shading Mode"},"sceneLighting":true,"audioPlay":false,"sceneViewState":{"m_AlwaysRefresh":false,"showFog":true,"showSkybox":true,"showFlares":true,"showImageEffects":true,"showParticleSystems":true,"showVisualEffectGraphs":true,"m_FxEnabled":true},"in2DMode":false,"pivot":{"x":-2.0324108600616457,"y":-1.66781485080719,"z":7.972609519958496},"rotation":{"x":-0.661830484867096,"y":-0.004041779320687056,"z":0.0035841879434883596,"w":-0.7495759725570679},"size":12.121491432189942,"orthographic":false}